regina/libgmpxx.4.dylib
regina/__init__.py
regina/test.py
regina/sageSetup.py
regina/engine.cpython-39-darwin.so
regina/libgmp.10.dylib
regina/plainCompleter.py
regina/pyCensus/closed-hyp-census-full.tdb
regina/pyCensus/cusped-hyp-nor-census-9.tdb
regina/pyCensus/closed-nor-census-11.tdb
regina/pyCensus/__init__.py
regina/pyCensus/christy-knots-links.tdb
regina/pyCensus/cusped-hyp-or-census-9.tdb
regina/pyCensus/closed-or-census-11.tdb
regina/sageRegina/config.py
regina/sageRegina/version.py
regina/sageRegina/__init__.py
regina/sageRegina/test.py
regina/sageRegina/testsuite/plantri.test
regina/sageRegina/testsuite/discs.out
regina/sageRegina/testsuite/memory2.out
regina/sageRegina/testsuite/lst.out
regina/sageRegina/testsuite/equality.out
regina/sageRegina/testsuite/hash.test
regina/sageRegina/testsuite/snapshot.out
regina/sageRegina/testsuite/memory3.out
regina/sageRegina/testsuite/snappea.test
regina/sageRegina/testsuite/file.out
regina/sageRegina/testsuite/italian.orb
regina/sageRegina/testsuite/groups.test
regina/sageRegina/testsuite/memory1.out
regina/sageRegina/testsuite/skeleton.test
regina/sageRegina/testsuite/bytes.test
regina/sageRegina/testsuite/testbasic.in
regina/sageRegina/testsuite/flype.out
regina/sageRegina/testsuite/safeheldtype_basic.out
regina/sageRegina/testsuite/arrow.out
regina/sageRegina/testsuite/equality.test
regina/sageRegina/testsuite/pdf.test
regina/sageRegina/testsuite/CMakeLists.txt
regina/sageRegina/testsuite/safeheldtype_packet.out
regina/sageRegina/testsuite/utf8.test
regina/sageRegina/testsuite/census.test
regina/sageRegina/testsuite/trigeneral.out
regina/sageRegina/testsuite/comparison.out
regina/sageRegina/testsuite/listener.out
regina/sageRegina/testsuite/memory1.test
regina/sageRegina/testsuite/alltypes.test
regina/sageRegina/testsuite/euler.out
regina/sageRegina/testsuite/census.out
regina/sageRegina/testsuite/poincare.tri
regina/sageRegina/testsuite/dodec.orb
regina-7.4.1.dist-info/RECORD
regina-7.4.1.dist-info/WHEEL
regina-7.4.1.dist-info/top_level.txt
regina-7.4.1.dist-info/METADATA
