Metadata-Version: 2.4
Name: regina
Version: 7.4.1
Summary: Regina-Normal
Home-page: http://github.com/3-manifolds/regina_wheels
Author: The Regina developers, Marc Culler, Nathan Dunfield, and Matthias Goerner
Author-email: snappy-help@computop.org
License: GPLv2+
Keywords: triangulations,topology
Classifier: Development Status :: 3 - Alpha
Classifier: Intended Audience :: Science/Research
Classifier: License :: OSI Approved :: GNU General Public License v2 or later (GPLv2+)
Classifier: Operating System :: POSIX :: Linux
Classifier: Operating System :: MacOS :: MacOS X
Classifier: Programming Language :: C
Classifier: Programming Language :: C++
Classifier: Programming Language :: Python
Classifier: Programming Language :: Cython
Classifier: Topic :: Scientific/Engineering :: Mathematics
Requires-Python: >=3.6
Dynamic: author
Dynamic: author-email
Dynamic: classifier
Dynamic: description
Dynamic: description-content-type
Dynamic: home-page
Dynamic: keywords
Dynamic: license
Dynamic: requires-python
Dynamic: summary
